README.md
setup.py
py_vncorenlp/__init__.py
py_vncorenlp/vncorenlp.py
py_vncorenlp.egg-info/PKG-INFO
py_vncorenlp.egg-info/SOURCES.txt
py_vncorenlp.egg-info/dependency_links.txt
py_vncorenlp.egg-info/requires.txt
py_vncorenlp.egg-info/top_level.txt