Metadata-Version: 2.1
Name: py-vncorenlp
Version: 0.1.1
Summary: A Python Wrapper for VnCoreNLP
Home-page: https://github.com/thelinhbkhn2014/VnCoreNLP_Wrapper
Author: Linh The Nguyen
Author-email: toank45sphn@gmail.com
Maintainer: linhthenguyen
Maintainer-email: toank45sphn@gmail.com
License: UNKNOWN
Platform: UNKNOWN
Classifier: Development Status :: 4 - Beta
Classifier: Intended Audience :: Developers
Classifier: License :: OSI Approved :: MIT License
Classifier: Programming Language :: Python :: 3.6
Requires-Python: >=3.6
